releasecraft-0.3.0rc1.dist-info/licenses/LICENSE
releaser/__init__.py
releaser/cli.py
releaser/commit_gen.py
releaser/commit_lint.py
releaser/console.py
releaser/init_cmd.py
releaser/workflow.py
releaser/ai/__init__.py
releaser/ai/cache.py
releaser/ai/config.py
releaser/ai/data_collector.py
releaser/ai/generator.py
releaser/ai/schemas.py
releaser/ai/engine/__init__.py
releaser/ai/engine/openai_instructor.py
releaser/ai/prompts/__init__.py
releaser/bump/__init__.py
releaser/bump/flow.py
releaser/bump/notes.py
releaser/bump/providers.py
releaser/bump/rules.py
releaser/bump/semver.py
releaser/config/__init__.py
releaser/config/load.py
releaser/config/model.py
releaser/drafter/utils.py
releaser/log/__init__.py
releaser/log/capture.py
releaser/log/cli_parser.py
releaser/log/client.py
releaser/log/modes.py
releaser/log/streaming.py
releaser/log/tunnel.py
releaser/log/utils.py
releasecraft-0.3.0rc1.dist-info/METADATA
releasecraft-0.3.0rc1.dist-info/WHEEL
releasecraft-0.3.0rc1.dist-info/entry_points.txt
releasecraft-0.3.0rc1.dist-info/top_level.txt
releasecraft-0.3.0rc1.dist-info/RECORD
