Metadata-Version: 2.4
Name: releasecraft
Version: 0.3.0rc1
Summary: A CLI tool for generating releases and changelogs, and streaming out stdout in a fancy way.
Author-email: haonguyen <vanhao1915@gmail.com>
License: MIT
Classifier: Development Status :: 3 - Alpha
Classifier: Intended Audience :: Developers
Classifier: License :: OSI Approved :: MIT License
Classifier: Programming Language :: Python :: 3
Classifier: Programming Language :: Python :: 3.9
Classifier: Programming Language :: Python :: 3.10
Classifier: Programming Language :: Python :: 3.11
Classifier: Programming Language :: Python :: 3.12
Requires-Python: <4.0,>=3.9
License-File: LICENSE
Requires-Dist: click>=8.0.0
Requires-Dist: requests>=2.25.0
Requires-Dist: PyYAML>=5.4.0
Requires-Dist: GitPython>=3.1.0
Requires-Dist: tabulate>=0.8.7
Requires-Dist: packaging>=20.0
Requires-Dist: pyfiglet==1.0.3
Requires-Dist: matplotlib>=3.3.0
Requires-Dist: python-socketio==5.13.0
Requires-Dist: toml<0.11.0,>=0.10.2
Requires-Dist: instructor<2.0.0,>=1.13.0
Provides-Extra: dev
Requires-Dist: pytest>=7.0.0; extra == "dev"
Requires-Dist: pytest-cov>=4.0.0; extra == "dev"
Requires-Dist: black>=22.0.0; extra == "dev"
Requires-Dist: flake8>=5.0.0; extra == "dev"
Requires-Dist: mypy>=1.0.0; extra == "dev"
Dynamic: license-file
